unitvalue/__init__.py
unitvalue/units.py
UnitValues-0.1.4.dist-info/LICENSE
UnitValues-0.1.4.dist-info/METADATA
UnitValues-0.1.4.dist-info/WHEEL
UnitValues-0.1.4.dist-info/top_level.txt
UnitValues-0.1.4.dist-info/RECORD
